{
  "$schema" : "https:\/\/app.linearmouse.org\/schema\/0.7.3",
  "schemes" : [
    {
      "pointer" : {
        "acceleration" : 0,
        "speed" : 0.4,
        "disableAcceleration" : true
      },
      "if" : {
        "device" : {
          "productName" : "USB Receiver",
          "productID" : "0xc548",
          "category" : "mouse",
          "vendorID" : "0x46d"
        }
      },
      "scrolling" : {
        "reverse" : {
          "vertical" : true
        },
        "distance" : 3
      }
    },
    {
      "pointer" : {
        "acceleration" : 0,
        "speed" : 0.3,
        "disableAcceleration" : true
      },
      "if" : {
        "device" : {
          "productName" : "USB Optical Mouse",
          "productID" : "0xc077",
          "category" : "mouse",
          "vendorID" : "0x46d"
        }
      },
      "scrolling" : {
        "reverse" : {
          "vertical" : true
        }
      }
    }
  ]
}